checol/__init__.py
checol/__main__.py
checol/main.py
checol/vcs.py
checol/gpt/__init__.py
checol/gpt/base_model.py
checol/gpt/chat_gpt.py
checol/gpt/claude.py
checol-0.4.0.dist-info/METADATA
checol-0.4.0.dist-info/WHEEL
checol-0.4.0.dist-info/entry_points.txt
checol-0.4.0.dist-info/licenses/LICENSE
checol-0.4.0.dist-info/RECORD
