Metadata-Version: 2.3
Name: checol
Version: 0.4.0
Author-email: HAYASAKA Ryosuke <hayasaka.ryosuke@gmail.com>
License-File: LICENSE
Requires-Python: >=3.8
Requires-Dist: anthropic>=0.21.3
Requires-Dist: fire>=0.6.0
Requires-Dist: gitpython>=3.1.42
Requires-Dist: halo>=0.0.31
Requires-Dist: openai>=1.38.0
Requires-Dist: prompt-toolkit>=3.0.43
Requires-Dist: python-dotenv>=1.0.1
